wezel/__init__.py
wezel/api.py
wezel/gui.py
wezel/canvas/__init__.py
wezel/canvas/canvas.py
wezel/canvas/image_filter.py
wezel/canvas/mask_filter.py
wezel/canvas/scene_filter.py
wezel/canvas/series_canvas.py
wezel/canvas/toolbar.py
wezel/canvas/utils.py
wezel/displays/__init__.py
wezel/displays/dicom_header.py
wezel/displays/plot_display.py
wezel/displays/series_display.py
wezel/displays/series_display_4d.py
wezel/displays/table_display.py
wezel/icons/__init__.py
wezel/icons/inventory.py
wezel/icons/fugue_icons/__init__.py
wezel/icons/fugue_icons/animal-dog.png
wezel/icons/fugue_icons/application-import.png
wezel/icons/fugue_icons/arrow-curve-180-left.png
wezel/icons/fugue_icons/arrow-curve.png
wezel/icons/fugue_icons/arrow-in.png
wezel/icons/fugue_icons/arrow-move.png
wezel/icons/fugue_icons/arrow-out.png
wezel/icons/fugue_icons/arrow-resize-090.png
wezel/icons/fugue_icons/arrow-stop-090.png
wezel/icons/fugue_icons/arrow-stop-270.png
wezel/icons/fugue_icons/bin-metal.png
wezel/icons/fugue_icons/blue-document-export.png
wezel/icons/fugue_icons/brightness.png
wezel/icons/fugue_icons/bug.png
wezel/icons/fugue_icons/clipboard--plus.png
wezel/icons/fugue_icons/color--arrow.png
wezel/icons/fugue_icons/color.png
wezel/icons/fugue_icons/contrast-low.png
wezel/icons/fugue_icons/contrast.png
wezel/icons/fugue_icons/controller-d-pad.png
wezel/icons/fugue_icons/cross-script.png
wezel/icons/fugue_icons/cursor.png
wezel/icons/fugue_icons/cutter.png
wezel/icons/fugue_icons/disk.png
wezel/icons/fugue_icons/document-excel-csv.png
wezel/icons/fugue_icons/document-excel.png
wezel/icons/fugue_icons/eraser--arrow.png
wezel/icons/fugue_icons/eraser--plus.png
wezel/icons/fugue_icons/eraser.png
wezel/icons/fugue_icons/hand-finger.png
wezel/icons/fugue_icons/hand-point-090.png
wezel/icons/fugue_icons/hand.png
wezel/icons/fugue_icons/layer-select.png
wezel/icons/fugue_icons/layer-shape-curve.png
wezel/icons/fugue_icons/layer-shape-ellipse.png
wezel/icons/fugue_icons/layer-shape-polygon.png
wezel-0.1.4.dist-info/LICENSE
wezel-0.1.4.dist-info/METADATA
wezel-0.1.4.dist-info/WHEEL
wezel-0.1.4.dist-info/top_level.txt
wezel-0.1.4.dist-info/RECORD
